setup.py
gillcup_graphics/__init__.py
gillcup_graphics/debugger.py
gillcup_graphics/effectlayer.py
gillcup_graphics/mainwindow.py
gillcup_graphics/objects.py
gillcup_graphics/transformation.py
gillcup_graphics.egg-info/PKG-INFO
gillcup_graphics.egg-info/SOURCES.txt
gillcup_graphics.egg-info/dependency_links.txt
gillcup_graphics.egg-info/requires.txt
gillcup_graphics.egg-info/top_level.txt
gillcup_graphics/offscreen/__init__.py
gillcup_graphics/offscreen/fbo.py
gillcup_graphics/test/__init__.py
gillcup_graphics/test/test_debugger.py
gillcup_graphics/test/test_rectangle.py
gillcup_graphics/test/test_sprite.py
gillcup_graphics/test/test_tests.py
gillcup_graphics/test/test_text.py
gillcup_graphics/test/test_transformation.py
gillcup_graphics/test/testlayer.py
gillcup_graphics/test/util.py